{
    "packages/button": "1.1.0",
    "packages/core": "3.2.1",
    "packages/countdown": "2.0.5",
    "packages/design": "1.0.5",
    "packages/elements": "1.2.4",
    "packages/forms": "5.2.2",
    "packages/gravatar": "2.0.6",
    "packages/icon": "1.0.2",
    "packages/link": "2.0.2",
    "packages/list": "1.0.5",
    "packages/locale": "1.0.1",
    "packages/navigation": "4.0.3",
    "packages/nuxt": "1.1.1",
    "packages/overlays": "1.1.1",
    "packages/pagination": "2.1.4",
    "packages/placeholder": "1.0.5",
    "packages/table": "1.2.2",
    "themes/bootstrap": "7.0.2",
    "themes/bulma": "5.0.1",
    "themes/tailwind": "6.0.0",
    "icons/font-awesome": "1.1.2",
    "icons/lucide": "1.1.2",
    "packages/timeago": "2.1.1",
    "examples/nuxt": "6.1.2"
}
