{"components_alert.md":"BUGthZKU","components_aspect-ratio.md":"y_olMIdF","components_avatar.md":"Bhe9Qny5","components_badge.md":"u8r540oh","components_button.md":"DyAwvGWH","components_card.md":"BAoeDdLt","components_collapse.md":"CNjwjkRW","components_context-menu.md":"Dct04_7H","components_countdown.md":"BlH7W0tf","components_dropdown-menu.md":"Dp7cnD5P","components_form-checkbox.md":"CPQWIcDI","components_form-input.md":"y4or2dhr","components_form-number.md":"CP2SPUqX","components_form-pin.md":"Cpu-dC-E","components_form-radio.md":"dClnNYjs","components_form-select-search.md":"Dnse47GN","components_form-select.md":"CjY6f-ou","components_form-slider.md":"fUjxKzCp","components_form-switch.md":"BrtFdmqQ","components_form-tags.md":"BdBp_OwK","components_form-textarea.md":"CJfLfssA","components_gravatar.md":"BRWDVHit","components_hover-card.md":"KDRg41Vv","components_icon.md":"DLIWa7f4","components_index.md":"dSM40XOJ","components_link.md":"DREqOHQS","components_list.md":"C8i0MdJT","components_modal.md":"BdTqND3R","components_navigation.md":"BRlrRT4C","components_pagination.md":"DOvw9RnM","components_placeholder.md":"Bitii2Ry","components_popover.md":"ayFYb2Wd","components_separator.md":"rXBN_J2k","components_stepper.md":"mE_ocp1m","components_table.md":"DU7KLQf-","components_tag.md":"BklkxILx","components_timeago.md":"DXgu-hYO","components_toast.md":"yNsNsBRy","components_tooltip.md":"DqcpD_S6","components_visually-hidden.md":"DRyf3NAP","getting-started_dark-mode.md":"D468EL2n","getting-started_icons.md":"CjG57YLq","getting-started_index.md":"CDgaYmZ7","getting-started_installation.md":"33bOftZU","getting-started_theming.md":"VHex8kx6","guide_behavioral-defaults.md":"CyxGnPOG","guide_build-themable-component.md":"BNkj4DkR","guide_composables.md":"DxfZb-wQ","guide_composing-themes.md":"BDuGiKZH","guide_design-tokens.md":"Ccc1JYX_","guide_index.md":"BDqDxxK1","guide_navigation-manager.md":"DQmsRf6D","guide_primitive.md":"C6AqBWBO","guide_theme-system.md":"t0MNUxaz","guide_variants.md":"Bhht25Zz","icons_font-awesome.md":"CayLWL0E","icons_index.md":"B0SlL1OL","icons_lucide.md":"kYXQwC_3","index.md":"DKVnKVCW","nuxt_index.md":"BjlHqGSm","nuxt_use-color-mode.md":"MBhpN16x","nuxt_use-palette.md":"B9lQiAWA","themes_bootstrap.md":"C1mRxHs7","themes_bulma.md":"BhiSA_QD","themes_index.md":"O32AvnuY","themes_tailwind.md":"CbZRMlrR"}
