{"components_countdown.md":"CH5FbGzP","components_form-checkbox.md":"XJRrE4BD","components_form-input.md":"BuxMPzSv","components_form-range-slider.md":"Dw05t4av","components_form-select-search.md":"BbPN4ytG","components_form-select.md":"B53l0ojt","components_form-submit.md":"DLKsosAe","components_form-textarea.md":"CfUtEHLQ","components_gravatar.md":"DOPSvdCL","components_index.md":"dcH0efJV","components_link.md":"D26qmSc3","components_list-controls.md":"D3kvDC0T","components_navigation.md":"BMKnIcke","components_pagination.md":"w8JRYEQQ","components_timeago.md":"D0sDDvRg","getting-started_dark-mode.md":"DIOxgbhp","getting-started_index.md":"CzY_O31X","getting-started_installation.md":"D1EQG1hF","getting-started_theming.md":"DDDe6xum","guide_behavioral-defaults.md":"Dt8hmGMp","guide_design-tokens.md":"Ck5jPSFq","guide_index.md":"C2YZX417","guide_navigation-manager.md":"DGE-Cvun","guide_theme-system.md":"CluWJU7C","guide_variants.md":"BR-d0ILo","index.md":"B02g7Lq8","nuxt_index.md":"VJiLge3T","nuxt_use-color-mode.md":"qJWswN6N","nuxt_use-palette.md":"ZjTkLUC7","themes_bootstrap-v4.md":"ByyVRBif","themes_bootstrap-v5.md":"DJgsBL7I","themes_font-awesome.md":"Dkv3xhfX","themes_index.md":"B0mbmfQ4","themes_tailwind.md":"Dv2o3Y2W"}
